mplanetypes/__init__.py
mplanetypes-0.1.dist-info/METADATA
mplanetypes-0.1.dist-info/WHEEL
mplanetypes-0.1.dist-info/top_level.txt
mplanetypes-0.1.dist-info/RECORD
